vulkan/__init__.py
vulkan/auth.py
vulkan/connections.py
vulkan/credentials.py
vulkan/data_source.py
vulkan/exceptions.py
vulkan/http_client.py
vulkan/node_config.py
vulkan/schemas.py
vulkan/core/__init__.py
vulkan/core/context.py
vulkan/core/policy.py
vulkan/core/resolution.py
vulkan/core/run.py
vulkan/core/step_metadata.py
vulkan/core/backtest/__init__.py
vulkan/core/backtest/definitions.py
vulkan/core/backtest/metrics.py
vulkan/runners/__init__.py
vulkan/runners/beam/__init__.py
vulkan/runners/beam/context.py
vulkan/runners/beam/io.py
vulkan/runners/beam/nodes.py
vulkan/runners/beam/pipeline.py
vulkan/runners/beam/local/__init__.py
vulkan/runners/beam/local/run_node.py
vulkan/runners/beam/local/runner.py
vulkan/runners/beam/metrics/__init__.py
vulkan/runners/beam/metrics/binary.py
vulkan/runners/beam/metrics/pipeline.py
vulkan/runners/beam/test/input_data.csv
vulkan/runners/beam/test/results_data.csv
vulkan/runners/beam/test/test_beam_nodes.py
vulkan/runners/dagster/__init__.py
vulkan/runners/dagster/io_manager.py
vulkan/runners/dagster/names.py
vulkan/runners/dagster/nodes.py
vulkan/runners/dagster/policy.py
vulkan/runners/dagster/resources.py
vulkan/runners/dagster/run_config.py
vulkan/runners/dagster/workspace.py
vulkan/runners/dagster/test/test_dagster_nodes.py
vulkan/runners/hatchet/__init__.py
vulkan/runners/hatchet/nodes.py
vulkan/runners/hatchet/policy.py
vulkan/runners/hatchet/workspace.py
vulkan/runners/hatchet/test/test_hatchet_nodes.py
vulkan/runners/shared/__init__.py
vulkan/runners/shared/app_client.py
vulkan/runners/shared/constants.py
vulkan/runners/shared/decision_fn.py
vulkan/runners/shared/run_config.py
vulkan/spec/__init__.py
vulkan/spec/context.py
vulkan/spec/dependency.py
vulkan/spec/graph.py
vulkan/spec/policy.py
vulkan/spec/environment/__init__.py
vulkan/spec/environment/config.py
vulkan/spec/environment/loaders.py
vulkan/spec/environment/packing.py
vulkan/spec/environment/workspace.py
vulkan/spec/nodes/__init__.py
vulkanlabs_vulkan-0.1.0.dev20251119095008.dist-info/METADATA
vulkanlabs_vulkan-0.1.0.dev20251119095008.dist-info/WHEEL
vulkanlabs_vulkan-0.1.0.dev20251119095008.dist-info/RECORD
