Metadata-Version: 2.4
Name: vulkanlabs-vulkan
Version: 0.1.0.dev20251119095008
Requires-Dist: graphviz>=0.20.3
Requires-Dist: httpx>=0.27.0
Requires-Dist: jinja2>=3.1.6
Requires-Dist: networkx>=3.4.2
Requires-Dist: pydantic>=2.9.2
Requires-Dist: pyjwt>=2.10.1
Requires-Dist: pyyaml>=6.0.2
Requires-Dist: tenacity>=8.5.0
Provides-Extra: beam
Requires-Dist: apache-beam[dataframe,gcp]>=2.69.0; extra == 'beam'
Provides-Extra: dagster
Requires-Dist: dagster-postgres>=0.27.9; extra == 'dagster'
Requires-Dist: dagster>=1.11.9; extra == 'dagster'
Provides-Extra: hatchet
Requires-Dist: hatchet-sdk>=1.16; extra == 'hatchet'
